skillset/__init__.py
skillset/__main__.py
skillset/builtins.py
skillset/cli.py
skillset-0.2.0.dist-info/METADATA
skillset-0.2.0.dist-info/WHEEL
skillset-0.2.0.dist-info/entry_points.txt
skillset-0.2.0.dist-info/top_level.txt
skillset-0.2.0.dist-info/RECORD
