Metadata-Version: 2.4
Name: skillset
Version: 0.2.0
Summary: Manage AI skills and permissions across different projects
Requires-Python: >=3.11
